what_msg_sender/__init__.py
whatmsgsender/__init__.py
whatmsgsender-0.1.dist-info/Licence.txt
whatmsgsender-0.1.dist-info/METADATA
whatmsgsender-0.1.dist-info/WHEEL
whatmsgsender-0.1.dist-info/top_level.txt
whatmsgsender-0.1.dist-info/RECORD
