Metadata-Version: 2.1
Name: whatmsgsender
Version: 0.1
Summary: this module help to sheule whatsapp msg and send on time
Home-page: https://sujalnas.ml
Author: sujal
Author-email: sujalchaudhary63@gmail.com
License: MIT
Keywords: whatsapp,whatsapp sheduler,whatsapp messenger
Platform: UNKNOWN
Classifier: Development Status :: 3 - Alpha
Classifier: Intended Audience :: Developers
Classifier: Topic :: Software Development :: Build Tools
Classifier: License :: OSI Approved :: MIT License
Classifier: Programming Language :: Python :: 3
Classifier: Programming Language :: Python :: 3.4
Classifier: Programming Language :: Python :: 3.5
Classifier: Programming Language :: Python :: 3.6
License-File: Licence.txt
Requires-Dist: pyautogui
